eliana/datasets/__init__.py
eliana/datasets/eliana_dataset.py
eliana/datasets/logparsers.py
eliana/datasets/parlogs_observations.py
eliana/models/Strangelog.py
eliana/models/__init__.py
eliana/preprocessing/__init__.py
eliana/preprocessing/log_colorizer.py
eliana/preprocessing/optimizer_vector.py
eliana/preprocessing/tokenizers.py
eliana/preprocessing/utils.py
eliana-0.1.8.dist-info/LICENSE
eliana-0.1.8.dist-info/METADATA
eliana-0.1.8.dist-info/WHEEL
eliana-0.1.8.dist-info/top_level.txt
eliana-0.1.8.dist-info/RECORD
