Metadata-Version: 2.1
Name: eliana
Version: 0.1.8
Summary: ELIANA (Event Log and Incident Analysis), a log analysis library developed at the Paranal Observatory
Author-email: Juan Pablo Gil <juanpablo.gil@eso.org>
License: BSD License
Project-URL: Homepage, https://github.com/paranal-sw/eliana
Project-URL: Repository, https://github.com/paranal-sw/eliana
Classifier: Programming Language :: Python :: 3
Classifier: License :: OSI Approved :: BSD License
Classifier: Operating System :: OS Independent
Requires-Python: >=3.6.8
License-File: LICENSE
Requires-Dist: pandas
Requires-Dist: matplotlib
Requires-Dist: numpy
Requires-Dist: scikit-learn
Requires-Dist: pyarrow
Requires-Dist: fastparquet
